[{"type":"d","name":"Lendy Key- Student Loan","balance":63000,"minPayment":650,"actualPayment":650,"rate":4.75,"overpay":0,"installments":123,"interest":16626.649999999994},{"type":"d","name":"Americor","balance":7000,"minPayment":330,"actualPayment":330,"rate":5,"overpay":0,"installments":23,"interest":344.27},{"type":"d","name":"Fed Loan Servicing","balance":14000,"minPayment":150,"actualPayment":150,"rate":0,"overpay":0,"installments":94,"interest":0},{"type":"d","name":401,"balance":6500,"minPayment":205.16,"actualPayment":205.16,"rate":7.5,"overpay":0,"installments":36,"interest":766.3100000000002},{"type":"d","name":"Jonestown Bank Car Loan","balance":22000,"minPayment":447.88,"actualPayment":447.88,"rate":4.5,"overpay":0,"installments":55,"interest":2361.14},{"type":"d","name":"Affirm Credit Card","balance":1200,"minPayment":81.98,"actualPayment":81.98,"rate":29.99,"overpay":0,"installments":19,"interest":312.7499999999999}]